{"Subject":[
{"Name":"Sellers","Location":"","Articles":[
]},
{"Name":"Buyers","Location":"","Articles":[
	{"Name":"5 Reasons You Need a REALTOR","Location":"advice/5ReasonsYouNeedARealtor.php"},
	{"Name":"Questions to Ask When Choosing a REALTOR","Location":"advice/QuestionsToAskWhenChoosingARealtor.php"},
	{"Name":"5 Factors That Decide Your Credit Score","Location":"advice/5FactorsThatDecideYourCreditScore.php"},
	{"Name":"Choices That Will Affect Your Loan","Location":"advice/ChoicesThatWillAffectYourLoan.php"},
	{"Name":"Is Your Move Tax Deductible","Location":"advice/IsYourMoveTaxDeductible.php"},
	{"Name":"Tips on Buying in a Tight Market","Location":"advice/TipsOnBuyingInATightMarket.php"},
	{"Name":"The Pros and Cons of Condos","Location":"advice/TheProsAndConsOfCondos.php"},
	{"Name":"7 Reasons to Own Your Own Home","Location":"advice/7ReasonsToOwnYourOwnHome.php"},
	{"Name":"5 Common First-Time Homebuyer Mistakes","Location":"advice/5CommonFirstTimeHomebuyerMistakes.php"},
	{"Name":"10 Tips for First-Time Homebuyers","Location":"advice/10TipsForFirstTimeHomeBuyers.php"},
	{"Name":"10 Things to Take the Trauma Out of Homebuying","Location":"advice/10ThingsToTakeTheTraumaOutOfHomeBuying.php"},
	{"Name":"How High Tech Is Your Home?","Location":"advice/HowHighTechIsYourHome.php"},
	{"Name":"10 Steps to Prepare for Homeownership","Location":"advice/10StepsToPrepareforHomeOwnership.php"},
	{"Name":"8 Steps to Getting Your Finances in Order","Location":"advice/8StepsToGettingYourFinancesInOrder.php"},
	{"Name":"Cleaning Up Your Credit","Location":"advice/CleaningUpYourCredit.php"},
	{"Name":"8 Ways to Improve Your Credit","Location":"advice/8WaysToImproveYourCredit.php"},
	{"Name":"Budget Basics Work Sheet","Location":"advice/BudgetBasicsWorkSheet.php"},
	{"Name":"6 Creative Ways to Afford a Home","Location":"advice/6CreativeWaysToAffordAHome.php"},
	{"Name":"Mortgage Pre-Qualification","Location":"advice/MortgagePreQualification.php"},
	{"Name":"How Big a Mortgage Can I Afford","Location":"advice/HowBigAMortgageCanIAfford.php"},
	{"Name":"10 Things a Lender Needs From You","Location":"advice/10ThingsALenderNeedsFromYou.php"},
	{"Name":"10 Questions to Ask Your Lender","Location":"advice/10QuestionsToAskYourLender.php"},
	{"Name":"Your Property Wish List","Location":"advice/YourPropertyWishList.php"},
	{"Name":"Shopping For Home Plans","Location":"advice/ShoppingForHomePlans.php"},
	{"Name":"Tips for Finding the Perfect Neighborhood","Location":"advice/TipsForFindingThePerfectNeighborhood.php"},
	{"Name":"Making An Offer On A Home","Location":"advice/MakingAnOfferOnAHome.php"},
	{"Name":"Key Factors Of The Offering Price","Location":"advice/KeyFactorsOfTheOfferingPrice.php"},
	{"Name":"The Offer","Location":"advice/TheOffer.php"},
	{"Name":"5 Property Tax Questions You Need to Ask","Location":"advice/5PropertyTaxQuestionsYouNeedToAsk.php"},
	{"Name":"The Fine Art Of Negotiating A Lease","Location":"advice/TheFineArtOfNegotiatingALease.php"},
	{"Name":"10 Questions to Ask Your Condo Board","Location":"advice/10QuestionsToAskYourCondoBoard.php"},
	{"Name":"Hidden Home Defects to Watch For","Location":"advice/HiddenHomeDefectsToWatchFor.php"},
	{"Name":"Home Inspection Survival Guide","Location":"advice/HomeInspectionSurvivalGuide.php"},
	{"Name":"What Your Home Inspection Should Cover","Location":"advice/WhatYourHomeInspectionShouldCover.php"},
	{"Name":"10 Questions to Ask a Home Inspector","Location":"advice/10QuestionsToAskAHomeInspector.php"},
	{"Name":"Things To Consider When Getting A Mortgage","Location":"advice/ThingsToConsiderWhenGettingAMortgage.php"},
	{"Name":"Tips On Packing","Location":"advice/TipsOnPacking.php"},
	{"Name":"5 Things to Understand About Title Insurance","Location":"advice/5ThingsToUnderstandAboutTitleInsurance.php"},
	{"Name":"What Not to Overlook on a Final Walk-through","Location":"advice/WhatNotToOverlookOnAFinalWalkThrough.php"},
	{"Name":"Common Closing Costs for Buyers","Location":"advice/CommonClosingCostsForBuyers.php"},
	{"Name":"10 Ways to Lower Your Homeowners Insurance Costs","Location":"advice/10WaysToLowerYourHomeownersInsuranceCosts.php"},
	{"Name":"Ten Tips For A Mold-Free House","Location":"advice/TenTipsForAMoldFreeHouse.php"},
	{"Name":"Top Home Danger Zones","Location":"advice/TopHomeDangerZones.php"},
	{"Name":"Top Ten Home Improvement Topics","Location":"advice/TopTenHomeImprovementTopics.php"},
	{"Name":"6 Items to Have on Hand for the New Owners","Location":"advice/6ItemsToHaveOnHandForTheNewOwners.php"},
	{"Name":"How Comprehensive Is Your Home Warranty?","Location":"advice/HowComprehensiveIsYourHomeWarranty.php"},
	{"Name":"5 Things to Understand About Homeowners Insurance","Location":"advice/5ThingsToUnderstandAboutHomeownersInsurance.php"},
	{"Name":"What to Keep From Your Closing","Location":"advice/WhatToKeepFromYourClosing.php"}
]},
{"Name":"Miscellaneous Topics","Location":"","Articles":[
	{"Name":"Understanding Agency","Location":"advice/UnderstandingAgency.php"},
	{"Name":"Experience Matters","Location":"advice/ExperienceMatters.php"},
	{"Name":"Where America Lives","Location":"advice/WhereAmericaLives.php"},
	{"Name":"Big Payoff","Location":"advice/BigPayoff.php"},
	{"Name":"Are You Ready To Be A Landlord","Location":"advice/AreYouReadyToBeALandlord.php"},
	{"Name":"Buy Real Estate With Your IRA","Location":"advice/BuyRealEstateWithYourIRA.php"},
	{"Name":"Tips for Packing Like a Pro","Location":"advice/TipsForPackingLikeAPro.php"},
	{"Name":"Web Site Resources for Consumers","Location":"advice/WebSiteResourcesForConsumers.php"},
	{"Name":"Spring - Call to Action","Location":"advice/SpringCallToAction.php"}
]},
{"Name":"Flower Mound","Location":"","Articles":[
	{"Name":"Official Web Site","Location":"http://www.flower-mound.com/"},
	{"Name":"City Statistics","Location":"http://www.bestplaces.net/zip-code/Flower_Mound_TX-77502200000.aspx"},
	{"Name":"Public Libraries","Location":"http://nces.ed.gov/surveys/libraries/librarysearch/library_list.asp?Search=1&Zip=75022&Miles=15"},
	{"Name":"Local Schools","Location":"http://www.greatschools.net/modperl/bycity/TX/?stateselect=TX&name=&market=&rating=&fuzzy=1&city=Flower%20Mound&schlname=&link="},
	{"Name":"Elected Officials","Location":"http://capwiz.com/yo-demo/state/main/?state=TX&azip=75022&view=myofficials"},
	{"Name":"Flower Mound Construction Plans","Location":"http://www.flower-mound.com/construct/construct_info.php"}
]},
{"Name":"Lewisville","Location":"","Articles":[
	{"Name":"Official Web Site","Location":"http://www.cityoflewisville.com/"},
	{"Name":"City Statistics","Location":"http://www.bestplaces.net/zip-code/Lewisville_TX-77502900000.aspx"},
	{"Name":"Public Libraries","Location":"http://nces.ed.gov/surveys/libraries/librarysearch/library_list.asp?Search=1&Zip=75029&Miles=15"},
	{"Name":"Local Schools","Location":"http://www.greatschools.net/modperl/bycity/TX/?stateselect=TX&name=&market=&rating=&fuzzy=1&city=Lewisville&schlname=&link="},
	{"Name":"Elected Officials","Location":"http://capwiz.com/yo-demo/state/main/?state=TX&azip=75029&view=myofficials"}
]},
{"Name":"Highland Village","Location":"","Articles":[
	{"Name":"Official Web Site","Location":"http://www.highlandvillage.org/"},
	{"Name":"City Statistics","Location":"http://www.bestplaces.net/city/Highland_Village_TX-54833848000.aspx"},
	{"Name":"Local Schools","Location":"http://www.greatschools.net/modperl/bycity/TX/?stateselect=TX&name=&market=&rating=&fuzzy=1&city=Highland%20Village&schlname=&link="},
	{"Name":"Elected Officials","Location":"http://capwiz.com/yo-demo/state/main/?state=TX&azip=&view=myofficials"}
]}
],
"Areas":[
{"area":"Argyle"},
{"area":"Bridlewood"},
{"area":"Copper Canyon"},
{"area":"Dallas"},
{"area":"Denton"},
{"area":"Double Oak"},
{"area":"Flower Mound"},
{"area":"Fort Worth"},
{"area":"Highland Village"},
{"area":"Lantana"},
{"area":"Lewisville"}],
"ExpertAdvice":[
{"advice":"Buying a new House"},
{"advice":"Selling your existing House "},
{"advice":"Renting or Leasing"},
{"advice":"Market Analysis"},
{"advice":"Mortgage Loans"},
{"advice":"Best Deals on Mortgages"},
{"advice":"Low Down Payment Mortgages"},
{"advice":"Appraisals"},
{"advice":"Best Buys"},
{"advice":"Good Deals"},
{"advice":"Local Attractions"},
{"advice":"Local Schools"},
{"advice":"Great Reasons to Move Here"},
{"advice":"Neighborhood Information"},
{"advice":"Home Pricing Tips"},
{"advice":"Home Buying Advice"},
{"advice":"Information on Flower Mound, TX"}],
"Specializations":[
{"Specialization":"New Homes"},
{"Specialization":"Relocation"},
{"Specialization":"Vacation Homes"},
{"Specialization":"Foreclosures"},
{"Specialization":"Repossessions"},
{"Specialization":"Bank Owned Real Estate"},
{"Specialization":"Multi Family Income Property"},
{"Specialization":"Buyer Representation"}]}